helix/__init__.py
helix/__main__.py
helix/blueprint.py
helix/build.py
helix/component.py
helix/exceptions.py
helix/tests.py
helix/transform.py
helix/utils.py
helix/blueprints/__init__.py
helix/blueprints/cmake/CMakeLists.txt
helix/blueprints/cmake/__init__.py
helix/blueprints/cmake/cmake.py
helix/blueprints/cmake/main.c
helix/blueprints/cmake/static/CMakeLists.txt
helix/blueprints/cmake/static/__init__.py
helix/blueprints/cmake/static/static.py
helix/components/__init__.py
helix/components/attack/__init__.py
helix/components/attack/utils.py
helix/components/attack/collection/__init__.py
helix/components/attack/collection/screen_capture/__init__.py
helix/components/attack/collection/screen_capture/bitblt/__init__.py
helix/components/attack/collection/screen_capture/bitblt/bitblt.py
helix/components/attack/collection/screen_capture/bitblt/windows-screenshot-bitblt.cpp
helix/components/attack/collection/screen_capture/xlib/__init__.py
helix/components/attack/collection/screen_capture/xlib/linux-screenshot-xlib.cpp
helix/components/attack/collection/screen_capture/xlib/xlib.py
helix/components/attack/command_and_control/__init__.py
helix/components/attack/command_and_control/remote_file_copy/__init__.py
helix/components/attack/command_and_control/remote_file_copy/libcurl/__init__.py
helix/components/attack/command_and_control/remote_file_copy/libcurl/libcurl.py
helix/components/attack/command_and_control/remote_file_copy/libcurl/linux-download-libcurl.cpp
helix/components/attack/defense_evasion/__init__.py
helix/components/attack/defense_evasion/file_deletion/__init__.py
helix/components/attack/defense_evasion/file_deletion/deletefile/__init__.py
helix/components/attack/defense_evasion/file_deletion/deletefile/deletefile.py
helix/components/attack/defense_evasion/file_deletion/deletefile/windows-deletefile.cpp
helix/components/attack/defense_evasion/file_deletion/remove/__init__.py
helix/components/attack/defense_evasion/file_deletion/remove/linux-remove.cpp
helix-1.2.0.dist-info/LICENSE.txt
helix-1.2.0.dist-info/METADATA
helix-1.2.0.dist-info/WHEEL
helix-1.2.0.dist-info/entry_points.txt
helix-1.2.0.dist-info/top_level.txt
helix-1.2.0.dist-info/RECORD
