Metadata-Version: 2.1
Name: helix
Version: 1.2.0
Summary: A source code mutation/transformation framework
Home-page: https://github.com/helix-datasets/helix
Author: MIT Lincoln Laboratory
Author-email: helix@ll.mit.edu
License: MIT
Platform: UNKNOWN
Classifier: Development Status :: 5 - Production/Stable
Classifier: Environment :: Console
Classifier: Intended Audience :: Developers
Classifier: Intended Audience :: Science/Research
Classifier: License :: OSI Approved :: MIT License
Classifier: Operating System :: OS Independent
Classifier: Programming Language :: Python
Classifier: Programming Language :: Python :: 3
Classifier: Programming Language :: Python :: 3 :: Only
Classifier: Programming Language :: Python :: 3.6
Classifier: Programming Language :: Python :: 3.7
Classifier: Programming Language :: Python :: 3.8
Classifier: Programming Language :: Python :: 3.9
Classifier: Programming Language :: Python :: 3.10
Classifier: Topic :: Security
Classifier: Topic :: Software Development
Classifier: Topic :: Software Development :: Build Tools
Classifier: Topic :: Software Development :: Code Generators
Classifier: Topic :: Software Development :: Libraries :: Application Frameworks
Classifier: Topic :: Software Development :: Libraries :: Python Modules
Requires-Python: >=3.5
License-File: LICENSE.txt
Requires-Dist: filemagic
Provides-Extra: development
Requires-Dist: black ; extra == 'development'
Requires-Dist: flake8 ; extra == 'development'
Requires-Dist: pip-tools ; extra == 'development'
Requires-Dist: pre-commit ; extra == 'development'
Requires-Dist: sphinx ; extra == 'development'
Requires-Dist: sphinx-rtd-theme ; extra == 'development'
Provides-Extra: linux
Requires-Dist: uninstallable ; (platform_system != "Linux") and extra == 'linux'
Provides-Extra: testing
Requires-Dist: xmlrunner ; extra == 'testing'
Requires-Dist: flake8-formatter-junit-xml ; extra == 'testing'
Provides-Extra: windows
Requires-Dist: uninstallable ; (platform_system != "Windows") and extra == 'windows'
